{
  "metadata": {
    "naBzplcCode": "8808990093062",
    "naBzplcName": "왜관농협공판장",
    "extractedAt": "2025-09-11T05:48:26.638Z",
    "totalDays": 38,
    "totalItems": 38,
    "totalRecords": 83
  },
  "data": [
    {
      "date": "20250507",
      "items": [
        {
          "itemCode": "003005009999",
          "itemName": "마늘(기타)",
          "data": [
            {
              "판매일자": "2025/05/07",
              "품종": "마늘(기타)",
              "산지": "경북 칠곡군",
              "중량": "4",
              "등급": "1등",
              "수량": "37",
              "경락가": "8,500"
            },
            {
              "판매일자": "2025/05/07",
              "품종": "마늘(기타)",
              "산지": "경북 칠곡군",
              "중량": "2",
              "등급": "2등",
              "수량": "40",
              "경락가": "4,000"
            }
          ],
          "count": 2
        }
      ]
    },
    {
      "date": "20250510",
      "items": [
        {
          "itemCode": "003005009999",
          "itemName": "마늘(기타)",
          "data": [
            {
              "판매일자": "2025/05/10",
              "품종": "마늘(기타)",
              "산지": "경북 칠곡군",
              "중량": "4",
              "등급": "1등",
              "수량": "40",
              "경락가": "10,000"
            },
            {
              "판매일자": "2025/05/10",
              "품종": "마늘(기타)",
              "산지": "경북 칠곡군",
              "중량": "2",
              "등급": "2등",
              "수량": "24",
              "경락가": "5,000"
            }
          ],
          "count": 2
        }
      ]
    },
    {
      "date": "20250526",
      "items": [
        {
          "itemCode": "003005009999",
          "itemName": "마늘(기타)",
          "data": [
            {
              "판매일자": "2025/05/26",
              "품종": "마늘(기타)",
              "산지": "경북 칠곡군",
              "중량": "4",
              "등급": "1등",
              "수량": "35",
              "경락가": "11,500"
            },
            {
              "판매일자": "2025/05/26",
              "품종": "마늘(기타)",
              "산지": "경북 칠곡군",
              "중량": "2",
              "등급": "2등",
              "수량": "14",
              "경락가": "5,500"
            }
          ],
          "count": 2
        }
      ]
    },
    {
      "date": "20250529",
      "items": [
        {
          "itemCode": "003005009999",
          "itemName": "마늘(기타)",
          "data": [
            {
              "판매일자": "2025/05/29",
              "품종": "마늘(기타)",
              "산지": "경북 칠곡군",
              "중량": "4",
              "등급": "1등",
              "수량": "29",
              "경락가": "12,000"
            },
            {
              "판매일자": "2025/05/29",
              "품종": "마늘(기타)",
              "산지": "경북 칠곡군",
              "중량": "2",
              "등급": "2등",
              "수량": "27",
              "경락가": "6,600"
            }
          ],
          "count": 2
        }
      ]
    },
    {
      "date": "20250530",
      "items": [
        {
          "itemCode": "003005009999",
          "itemName": "마늘(기타)",
          "data": [
            {
              "판매일자": "2025/05/30",
              "품종": "마늘(기타)",
              "산지": "경북 칠곡군",
              "중량": "4",
              "등급": "1등",
              "수량": "7",
              "경락가": "12,200"
            },
            {
              "판매일자": "2025/05/30",
              "품종": "마늘(기타)",
              "산지": "경북 칠곡군",
              "중량": "5",
              "등급": "1등",
              "수량": "30",
              "경락가": "15,300"
            },
            {
              "판매일자": "2025/05/30",
              "품종": "마늘(기타)",
              "산지": "경북 칠곡군",
              "중량": "3",
              "등급": "2등",
              "수량": "4",
              "경락가": "8,000"
            },
            {
              "판매일자": "2025/05/30",
              "품종": "마늘(기타)",
              "산지": "경북 칠곡군",
              "중량": "3.5",
              "등급": "2등",
              "수량": "20",
              "경락가": "11,500"
            }
          ],
          "count": 4
        }
      ]
    },
    {
      "date": "20250602",
      "items": [
        {
          "itemCode": "003005009999",
          "itemName": "마늘(기타)",
          "data": [
            {
              "판매일자": "2025/06/02",
              "품종": "마늘(기타)",
              "산지": "경북 칠곡군",
              "중량": "3",
              "등급": "1등",
              "수량": "7",
              "경락가": "9,000"
            },
            {
              "판매일자": "2025/06/02",
              "품종": "마늘(기타)",
              "산지": "경북 칠곡군",
              "중량": "3.5",
              "등급": "1등",
              "수량": "35",
              "경락가": "13,000"
            },
            {
              "판매일자": "2025/06/02",
              "품종": "마늘(기타)",
              "산지": "경북 칠곡군",
              "중량": "4",
              "등급": "1등",
              "수량": "16",
              "경락가": "13,000"
            },
            {
              "판매일자": "2025/06/02",
              "품종": "마늘(기타)",
              "산지": "경북 칠곡군",
              "중량": "4",
              "등급": "1등",
              "수량": "27",
              "경락가": "12,000"
            },
            {
              "판매일자": "2025/06/02",
              "품종": "마늘(기타)",
              "산지": "경북 칠곡군",
              "중량": "4",
              "등급": "1등",
              "수량": "20",
              "경락가": "13,000"
            },
            {
              "판매일자": "2025/06/02",
              "품종": "마늘(기타)",
              "산지": "경북 칠곡군",
              "중량": "2",
              "등급": "2등",
              "수량": "31",
              "경락가": "7,000"
            },
            {
              "판매일자": "2025/06/02",
              "품종": "마늘(기타)",
              "산지": "경북 칠곡군",
              "중량": "3",
              "등급": "2등",
              "수량": "8",
              "경락가": "8,000"
            },
            {
              "판매일자": "2025/06/02",
              "품종": "마늘(기타)",
              "산지": "경북 칠곡군",
              "중량": "3",
              "등급": "2등",
              "수량": "7",
              "경락가": "8,500"
            }
          ],
          "count": 8
        }
      ]
    },
    {
      "date": "20250603",
      "items": [
        {
          "itemCode": "003005009999",
          "itemName": "마늘(기타)",
          "data": [
            {
              "판매일자": "2025/06/03",
              "품종": "마늘(기타)",
              "산지": "경북 칠곡군",
              "중량": "4",
              "등급": "1등",
              "수량": "13",
              "경락가": "13,500"
            },
            {
              "판매일자": "2025/06/03",
              "품종": "마늘(기타)",
              "산지": "경북 칠곡군",
              "중량": "3",
              "등급": "2등",
              "수량": "7",
              "경락가": "8,000"
            }
          ],
          "count": 2
        }
      ]
    },
    {
      "date": "20250605",
      "items": [
        {
          "itemCode": "003005009999",
          "itemName": "마늘(기타)",
          "data": [
            {
              "판매일자": "2025/06/05",
              "품종": "마늘(기타)",
              "산지": "경북 칠곡군",
              "중량": "3",
              "등급": "1등",
              "수량": "30",
              "경락가": "14,000"
            },
            {
              "판매일자": "2025/06/05",
              "품종": "마늘(기타)",
              "산지": "경북 칠곡군",
              "중량": "4",
              "등급": "1등",
              "수량": "5",
              "경락가": "16,000"
            },
            {
              "판매일자": "2025/06/05",
              "품종": "마늘(기타)",
              "산지": "경북 칠곡군",
              "중량": "5",
              "등급": "1등",
              "수량": "43",
              "경락가": "16,000"
            },
            {
              "판매일자": "2025/06/05",
              "품종": "마늘(기타)",
              "산지": "경북 칠곡군",
              "중량": "2",
              "등급": "2등",
              "수량": "16",
              "경락가": "8,000"
            },
            {
              "판매일자": "2025/06/05",
              "품종": "마늘(기타)",
              "산지": "경북 칠곡군",
              "중량": "3",
              "등급": "2등",
              "수량": "7",
              "경락가": "12,600"
            },
            {
              "판매일자": "2025/06/05",
              "품종": "마늘(기타)",
              "산지": "경북 칠곡군",
              "중량": "2",
              "등급": "3등",
              "수량": "18",
              "경락가": "7,000"
            }
          ],
          "count": 6
        }
      ]
    },
    {
      "date": "20250606",
      "items": [
        {
          "itemCode": "003005009999",
          "itemName": "마늘(기타)",
          "data": [
            {
              "판매일자": "2025/06/06",
              "품종": "마늘(기타)",
              "산지": "경북 칠곡군",
              "중량": "3",
              "등급": "1등",
              "수량": "46",
              "경락가": "16,000"
            },
            {
              "판매일자": "2025/06/06",
              "품종": "마늘(기타)",
              "산지": "경북 칠곡군",
              "중량": "4",
              "등급": "1등",
              "수량": "4",
              "경락가": "16,000"
            },
            {
              "판매일자": "2025/06/06",
              "품종": "마늘(기타)",
              "산지": "경북 칠곡군",
              "중량": "2",
              "등급": "2등",
              "수량": "14",
              "경락가": "6,500"
            },
            {
              "판매일자": "2025/06/06",
              "품종": "마늘(기타)",
              "산지": "경북 칠곡군",
              "중량": "3",
              "등급": "2등",
              "수량": "18",
              "경락가": "12,500"
            },
            {
              "판매일자": "2025/06/06",
              "품종": "마늘(기타)",
              "산지": "경북 칠곡군",
              "중량": "2",
              "등급": "3등",
              "수량": "8",
              "경락가": "5,000"
            }
          ],
          "count": 5
        }
      ]
    },
    {
      "date": "20250607",
      "items": [
        {
          "itemCode": "003005009999",
          "itemName": "마늘(기타)",
          "data": [
            {
              "판매일자": "2025/06/07",
              "품종": "마늘(기타)",
              "산지": "경북 칠곡군",
              "중량": "4",
              "등급": "1등",
              "수량": "23",
              "경락가": "15,000"
            },
            {
              "판매일자": "2025/06/07",
              "품종": "마늘(기타)",
              "산지": "경북 칠곡군",
              "중량": "3",
              "등급": "2등",
              "수량": "21",
              "경락가": "9,000"
            },
            {
              "판매일자": "2025/06/07",
              "품종": "마늘(기타)",
              "산지": "경북 칠곡군",
              "중량": "3",
              "등급": "혼합",
              "수량": "10",
              "경락가": "9,000"
            }
          ],
          "count": 3
        }
      ]
    },
    {
      "date": "20250609",
      "items": [
        {
          "itemCode": "003005009999",
          "itemName": "마늘(기타)",
          "data": [
            {
              "판매일자": "2025/06/09",
              "품종": "마늘(기타)",
              "산지": "경북 칠곡군",
              "중량": "3.5",
              "등급": "1등",
              "수량": "15",
              "경락가": "14,000"
            },
            {
              "판매일자": "2025/06/09",
              "품종": "마늘(기타)",
              "산지": "경북 칠곡군",
              "중량": "6",
              "등급": "1등",
              "수량": "4",
              "경락가": "17,000"
            },
            {
              "판매일자": "2025/06/09",
              "품종": "마늘(기타)",
              "산지": "경북 칠곡군",
              "중량": "2",
              "등급": "2등",
              "수량": "21",
              "경락가": "12,000"
            },
            {
              "판매일자": "2025/06/09",
              "품종": "마늘(기타)",
              "산지": "경북 칠곡군",
              "중량": "4",
              "등급": "2등",
              "수량": "4",
              "경락가": "14,000"
            }
          ],
          "count": 4
        }
      ]
    },
    {
      "date": "20250610",
      "items": [
        {
          "itemCode": "003005009999",
          "itemName": "마늘(기타)",
          "data": [
            {
              "판매일자": "2025/06/10",
              "품종": "마늘(기타)",
              "산지": "경북 칠곡군",
              "중량": "4",
              "등급": "1등",
              "수량": "31",
              "경락가": "15,000"
            },
            {
              "판매일자": "2025/06/10",
              "품종": "마늘(기타)",
              "산지": "경북 칠곡군",
              "중량": "3",
              "등급": "2등",
              "수량": "29",
              "경락가": "10,000"
            }
          ],
          "count": 2
        }
      ]
    },
    {
      "date": "20250611",
      "items": [
        {
          "itemCode": "003005009999",
          "itemName": "마늘(기타)",
          "data": [
            {
              "판매일자": "2025/06/11",
              "품종": "마늘(기타)",
              "산지": "경북 칠곡군",
              "중량": "3.5",
              "등급": "1등",
              "수량": "49",
              "경락가": "13,000"
            }
          ],
          "count": 1
        }
      ]
    },
    {
      "date": "20250612",
      "items": [
        {
          "itemCode": "003005009999",
          "itemName": "마늘(기타)",
          "data": [
            {
              "판매일자": "2025/06/12",
              "품종": "마늘(기타)",
              "산지": "경북 칠곡군",
              "중량": "3.5",
              "등급": "1등",
              "수량": "36",
              "경락가": "14,000"
            },
            {
              "판매일자": "2025/06/12",
              "품종": "마늘(기타)",
              "산지": "경북 칠곡군",
              "중량": "4",
              "등급": "1등",
              "수량": "30",
              "경락가": "12,500"
            },
            {
              "판매일자": "2025/06/12",
              "품종": "마늘(기타)",
              "산지": "경북 칠곡군",
              "중량": "4",
              "등급": "1등",
              "수량": "16",
              "경락가": "11,000"
            },
            {
              "판매일자": "2025/06/12",
              "품종": "마늘(기타)",
              "산지": "경북 칠곡군",
              "중량": "3",
              "등급": "2등",
              "수량": "45",
              "경락가": "8,500"
            }
          ],
          "count": 4
        }
      ]
    },
    {
      "date": "20250613",
      "items": [
        {
          "itemCode": "003005009999",
          "itemName": "마늘(기타)",
          "data": [
            {
              "판매일자": "2025/06/13",
              "품종": "마늘(기타)",
              "산지": "경북 칠곡군",
              "중량": "15",
              "등급": "1등",
              "수량": "8",
              "경락가": "30,000"
            }
          ],
          "count": 1
        }
      ]
    },
    {
      "date": "20250614",
      "items": [
        {
          "itemCode": "003005009999",
          "itemName": "마늘(기타)",
          "data": [
            {
              "판매일자": "2025/06/14",
              "품종": "마늘(기타)",
              "산지": "경북 칠곡군",
              "중량": "5",
              "등급": "1등",
              "수량": "10",
              "경락가": "18,000"
            }
          ],
          "count": 1
        }
      ]
    },
    {
      "date": "20250617",
      "items": [
        {
          "itemCode": "003005009999",
          "itemName": "마늘(기타)",
          "data": [
            {
              "판매일자": "2025/06/17",
              "품종": "마늘(기타)",
              "산지": "경북 칠곡군",
              "중량": "4",
              "등급": "1등",
              "수량": "10",
              "경락가": "16,000"
            },
            {
              "판매일자": "2025/06/17",
              "품종": "마늘(기타)",
              "산지": "경북 칠곡군",
              "중량": "3",
              "등급": "2등",
              "수량": "10",
              "경락가": "13,500"
            }
          ],
          "count": 2
        }
      ]
    },
    {
      "date": "20250620",
      "items": [
        {
          "itemCode": "003005009999",
          "itemName": "마늘(기타)",
          "data": [
            {
              "판매일자": "2025/06/20",
              "품종": "마늘(기타)",
              "산지": "경북 칠곡군",
              "중량": "3.5",
              "등급": "1등",
              "수량": "26",
              "경락가": "16,000"
            },
            {
              "판매일자": "2025/06/20",
              "품종": "마늘(기타)",
              "산지": "경북 칠곡군",
              "중량": "2",
              "등급": "2등",
              "수량": "12",
              "경락가": "12,000"
            }
          ],
          "count": 2
        }
      ]
    },
    {
      "date": "20250623",
      "items": [
        {
          "itemCode": "003005009999",
          "itemName": "마늘(기타)",
          "data": [
            {
              "판매일자": "2025/06/23",
              "품종": "마늘(기타)",
              "산지": "경북 칠곡군",
              "중량": "10",
              "등급": "특",
              "수량": "4",
              "경락가": "23,000"
            },
            {
              "판매일자": "2025/06/23",
              "품종": "마늘(기타)",
              "산지": "경북 칠곡군",
              "중량": "10",
              "등급": "상",
              "수량": "7",
              "경락가": "20,000"
            }
          ],
          "count": 2
        }
      ]
    },
    {
      "date": "20250624",
      "items": [
        {
          "itemCode": "003005009999",
          "itemName": "마늘(기타)",
          "data": [
            {
              "판매일자": "2025/06/24",
              "품종": "마늘(기타)",
              "산지": "경북 칠곡군",
              "중량": "3",
              "등급": "1등",
              "수량": "30",
              "경락가": "12,000"
            },
            {
              "판매일자": "2025/06/24",
              "품종": "마늘(기타)",
              "산지": "경북 칠곡군",
              "중량": "2",
              "등급": "2등",
              "수량": "30",
              "경락가": "8,000"
            }
          ],
          "count": 2
        }
      ]
    },
    {
      "date": "20250627",
      "items": [
        {
          "itemCode": "003005009999",
          "itemName": "마늘(기타)",
          "data": [
            {
              "판매일자": "2025/06/27",
              "품종": "마늘(기타)",
              "산지": "경북 칠곡군",
              "중량": "4",
              "등급": "1등",
              "수량": "10",
              "경락가": "17,000"
            }
          ],
          "count": 1
        }
      ]
    },
    {
      "date": "20250628",
      "items": [
        {
          "itemCode": "003005009999",
          "itemName": "마늘(기타)",
          "data": [
            {
              "판매일자": "2025/06/28",
              "품종": "마늘(기타)",
              "산지": "경북 칠곡군",
              "중량": "3",
              "등급": "1등",
              "수량": "4",
              "경락가": "15,000"
            },
            {
              "판매일자": "2025/06/28",
              "품종": "마늘(기타)",
              "산지": "경북 칠곡군",
              "중량": "2",
              "등급": "2등",
              "수량": "8",
              "경락가": "8,000"
            }
          ],
          "count": 2
        }
      ]
    },
    {
      "date": "20250701",
      "items": [
        {
          "itemCode": "003005009999",
          "itemName": "마늘(기타)",
          "data": [
            {
              "판매일자": "2025/07/01",
              "품종": "마늘(기타)",
              "산지": "경북 칠곡군",
              "중량": "4",
              "등급": "1등",
              "수량": "30",
              "경락가": "17,000"
            }
          ],
          "count": 1
        }
      ]
    },
    {
      "date": "20250704",
      "items": [
        {
          "itemCode": "003005009999",
          "itemName": "마늘(기타)",
          "data": [
            {
              "판매일자": "2025/07/04",
              "품종": "마늘(기타)",
              "산지": "경북 칠곡군",
              "중량": "4",
              "등급": "1등",
              "수량": "20",
              "경락가": "13,000"
            }
          ],
          "count": 1
        }
      ]
    },
    {
      "date": "20250705",
      "items": [
        {
          "itemCode": "003005009999",
          "itemName": "마늘(기타)",
          "data": [
            {
              "판매일자": "2025/07/05",
              "품종": "마늘(기타)",
              "산지": "경북 칠곡군",
              "중량": "5",
              "등급": "1등",
              "수량": "20",
              "경락가": "17,000"
            }
          ],
          "count": 1
        }
      ]
    },
    {
      "date": "20250708",
      "items": [
        {
          "itemCode": "003005009999",
          "itemName": "마늘(기타)",
          "data": [
            {
              "판매일자": "2025/07/08",
              "품종": "마늘(기타)",
              "산지": "경북 칠곡군",
              "중량": "4",
              "등급": "1등",
              "수량": "6",
              "경락가": "16,000"
            },
            {
              "판매일자": "2025/07/08",
              "품종": "마늘(기타)",
              "산지": "경북 칠곡군",
              "중량": "4",
              "등급": "2등",
              "수량": "8",
              "경락가": "18,000"
            }
          ],
          "count": 2
        }
      ]
    },
    {
      "date": "20250710",
      "items": [
        {
          "itemCode": "003005009999",
          "itemName": "마늘(기타)",
          "data": [
            {
              "판매일자": "2025/07/10",
              "품종": "마늘(기타)",
              "산지": "경북 칠곡군",
              "중량": "15",
              "등급": "1등",
              "수량": "1",
              "경락가": "44,000"
            },
            {
              "판매일자": "2025/07/10",
              "품종": "마늘(기타)",
              "산지": "경북 칠곡군",
              "중량": "15",
              "등급": "2등",
              "수량": "2",
              "경락가": "40,000"
            },
            {
              "판매일자": "2025/07/10",
              "품종": "마늘(기타)",
              "산지": "경북 칠곡군",
              "중량": "15",
              "등급": "3등",
              "수량": "1",
              "경락가": "28,000"
            },
            {
              "판매일자": "2025/07/10",
              "품종": "마늘(기타)",
              "산지": "경북 칠곡군",
              "중량": "15",
              "등급": "4등",
              "수량": "1",
              "경락가": "17,000"
            },
            {
              "판매일자": "2025/07/10",
              "품종": "마늘(기타)",
              "산지": "경북 칠곡군",
              "중량": "15",
              "등급": "특",
              "수량": "1",
              "경락가": "48,000"
            }
          ],
          "count": 5
        }
      ]
    },
    {
      "date": "20250712",
      "items": [
        {
          "itemCode": "003005009999",
          "itemName": "마늘(기타)",
          "data": [
            {
              "판매일자": "2025/07/12",
              "품종": "마늘(기타)",
              "산지": "경북 칠곡군",
              "중량": "3",
              "등급": "1등",
              "수량": "8",
              "경락가": "17,000"
            },
            {
              "판매일자": "2025/07/12",
              "품종": "마늘(기타)",
              "산지": "경북 칠곡군",
              "중량": "5",
              "등급": "2등",
              "수량": "8",
              "경락가": "15,000"
            }
          ],
          "count": 2
        }
      ]
    },
    {
      "date": "20250715",
      "items": [
        {
          "itemCode": "003005009999",
          "itemName": "마늘(기타)",
          "data": [
            {
              "판매일자": "2025/07/15",
              "품종": "마늘(기타)",
              "산지": "경북 칠곡군",
              "중량": "3",
              "등급": "1등",
              "수량": "20",
              "경락가": "13,000"
            }
          ],
          "count": 1
        }
      ]
    },
    {
      "date": "20250716",
      "items": [
        {
          "itemCode": "003005009999",
          "itemName": "마늘(기타)",
          "data": [
            {
              "판매일자": "2025/07/16",
              "품종": "마늘(기타)",
              "산지": "경북 칠곡군",
              "중량": "4",
              "등급": "1등",
              "수량": "13",
              "경락가": "15,000"
            }
          ],
          "count": 1
        }
      ]
    },
    {
      "date": "20250723",
      "items": [
        {
          "itemCode": "003005009999",
          "itemName": "마늘(기타)",
          "data": [
            {
              "판매일자": "2025/07/23",
              "품종": "마늘(기타)",
              "산지": "경북 칠곡군",
              "중량": "2",
              "등급": "1등",
              "수량": "7",
              "경락가": "13,000"
            },
            {
              "판매일자": "2025/07/23",
              "품종": "마늘(기타)",
              "산지": "경북 칠곡군",
              "중량": "3",
              "등급": "2등",
              "수량": "20",
              "경락가": "12,000"
            }
          ],
          "count": 2
        }
      ]
    },
    {
      "date": "20250726",
      "items": [
        {
          "itemCode": "003005009999",
          "itemName": "마늘(기타)",
          "data": [
            {
              "판매일자": "2025/07/26",
              "품종": "마늘(기타)",
              "산지": "경북 칠곡군",
              "중량": "5",
              "등급": "1등",
              "수량": "28",
              "경락가": "16,000"
            }
          ],
          "count": 1
        }
      ]
    },
    {
      "date": "20250807",
      "items": [
        {
          "itemCode": "003005009999",
          "itemName": "마늘(기타)",
          "data": [
            {
              "판매일자": "2025/08/07",
              "품종": "마늘(기타)",
              "산지": "경북 칠곡군",
              "중량": "2",
              "등급": "1등",
              "수량": "4",
              "경락가": "13,000"
            }
          ],
          "count": 1
        }
      ]
    },
    {
      "date": "20250809",
      "items": [
        {
          "itemCode": "003005009999",
          "itemName": "마늘(기타)",
          "data": [
            {
              "판매일자": "2025/08/09",
              "품종": "마늘(기타)",
              "산지": "경북 칠곡군",
              "중량": "3",
              "등급": "1등",
              "수량": "30",
              "경락가": "13,000"
            }
          ],
          "count": 1
        }
      ]
    },
    {
      "date": "20250811",
      "items": [
        {
          "itemCode": "003005009999",
          "itemName": "마늘(기타)",
          "data": [
            {
              "판매일자": "2025/08/11",
              "품종": "마늘(기타)",
              "산지": "경북 칠곡군",
              "중량": "2",
              "등급": "1등",
              "수량": "28",
              "경락가": "10,000"
            }
          ],
          "count": 1
        }
      ]
    },
    {
      "date": "20250816",
      "items": [
        {
          "itemCode": "003005009999",
          "itemName": "마늘(기타)",
          "data": [
            {
              "판매일자": "2025/08/16",
              "품종": "마늘(기타)",
              "산지": "경북 칠곡군",
              "중량": "2",
              "등급": "1등",
              "수량": "40",
              "경락가": "12,000"
            }
          ],
          "count": 1
        }
      ]
    },
    {
      "date": "20250830",
      "items": [
        {
          "itemCode": "003005009999",
          "itemName": "마늘(기타)",
          "data": [
            {
              "판매일자": "2025/08/30",
              "품종": "마늘(기타)",
              "산지": "경북 칠곡군",
              "중량": "2",
              "등급": "1등",
              "수량": "40",
              "경락가": "11,000"
            }
          ],
          "count": 1
        }
      ]
    },
    {
      "date": "20250906",
      "items": [
        {
          "itemCode": "003005009999",
          "itemName": "마늘(기타)",
          "data": [
            {
              "판매일자": "2025/09/06",
              "품종": "마늘(기타)",
              "산지": "경북 칠곡군",
              "중량": "2",
              "등급": "1등",
              "수량": "40",
              "경락가": "12,000"
            }
          ],
          "count": 1
        }
      ]
    }
  ]
}